Metadata-Version: 2.4
Name: llama-index-readers-steamship
Version: 0.4.1
Summary: llama-index readers steamship integration
Author-email: Your Name <you@example.com>
Maintainer: douglas-reid
License-Expression: MIT
License-File: LICENSE
Keywords: steamship
Requires-Python: <4.0,>=3.9
Requires-Dist: llama-index-core<0.15,>=0.13.0
